<annotation>
	<folder>熊猫1</folder>
	<filename>002555.jpg</filename>
	<path>C:\Users\asus\Desktop\熊猫1\002555.jpg</path>
	<source>
		<database>Unknown</database>
	</source>
	<size>
		<width>2848</width>
		<height>4200</height>
		<depth>3</depth>
	</size>
	<segmented>0</segmented>
	<object>
		<name>panda</name>
		<pose>Unspecified</pose>
		<truncated>0</truncated>
		<difficult>0</difficult>
		<bndbox>
			<xmin>126</xmin>
			<ymin>887</ymin>
			<xmax>2452</xmax>
			<ymax>4082</ymax>
		</bndbox>
	</object>
</annotation>
