<annotation>
	<folder>熊猫1</folder>
	<filename>002629.jpg</filename>
	<path>C:\Users\asus\Desktop\熊猫1\002629.jpg</path>
	<source>
		<database>Unknown</database>
	</source>
	<size>
		<width>3000</width>
		<height>2000</height>
		<depth>3</depth>
	</size>
	<segmented>0</segmented>
	<object>
		<name>panda</name>
		<pose>Unspecified</pose>
		<truncated>0</truncated>
		<difficult>0</difficult>
		<bndbox>
			<xmin>348</xmin>
			<ymin>80</ymin>
			<xmax>1776</xmax>
			<ymax>1876</ymax>
		</bndbox>
	</object>
	<object>
		<name>panda</name>
		<pose>Unspecified</pose>
		<truncated>0</truncated>
		<difficult>0</difficult>
		<bndbox>
			<xmin>998</xmin>
			<ymin>1037</ymin>
			<xmax>2455</xmax>
			<ymax>1998</ymax>
		</bndbox>
	</object>
</annotation>
