<annotation>
	<folder>熊猫2</folder>
	<filename>003018.jpg</filename>
	<path>C:\Users\asus\Desktop\熊猫2\003018.jpg</path>
	<source>
		<database>Unknown</database>
	</source>
	<size>
		<width>2336</width>
		<height>3504</height>
		<depth>3</depth>
	</size>
	<segmented>0</segmented>
	<object>
		<name>panda</name>
		<pose>Unspecified</pose>
		<truncated>1</truncated>
		<difficult>0</difficult>
		<bndbox>
			<xmin>15</xmin>
			<ymin>79</ymin>
			<xmax>2336</xmax>
			<ymax>3160</ymax>
		</bndbox>
	</object>
</annotation>
