<annotation>
	<folder>松鼠</folder>
	<filename>003657.jpg</filename>
	<path>D:\下载\松鼠\003657.jpg</path>
	<source>
		<database>Unknown</database>
	</source>
	<size>
		<width>299</width>
		<height>300</height>
		<depth>3</depth>
	</size>
	<segmented>0</segmented>
	<object>
		<name>squirrel</name>
		<pose>Unspecified</pose>
		<truncated>0</truncated>
		<difficult>0</difficult>
		<bndbox>
			<xmin>38</xmin>
			<ymin>17</ymin>
			<xmax>275</xmax>
			<ymax>271</ymax>
		</bndbox>
	</object>
</annotation>
