<annotation>
	<folder>老虎1</folder>
	<filename>005851.jpg</filename>
	<path>C:\Users\asus\Desktop\老虎1\005851.jpg</path>
	<source>
		<database>Unknown</database>
	</source>
	<size>
		<width>4928</width>
		<height>3264</height>
		<depth>3</depth>
	</size>
	<segmented>0</segmented>
	<object>
		<name>tiger</name>
		<pose>Unspecified</pose>
		<truncated>0</truncated>
		<difficult>0</difficult>
		<bndbox>
			<xmin>8</xmin>
			<ymin>402</ymin>
			<xmax>3972</xmax>
			<ymax>3120</ymax>
		</bndbox>
	</object>
</annotation>
