<annotation>
	<folder>大象</folder>
	<filename>007106.jpg</filename>
	<path>D:\下载\大象\007106.jpg</path>
	<source>
		<database>Unknown</database>
	</source>
	<size>
		<width>3500</width>
		<height>2334</height>
		<depth>3</depth>
	</size>
	<segmented>0</segmented>
	<object>
		<name>elephant</name>
		<pose>Unspecified</pose>
		<truncated>0</truncated>
		<difficult>0</difficult>
		<bndbox>
			<xmin>1121</xmin>
			<ymin>467</ymin>
			<xmax>2659</xmax>
			<ymax>1781</ymax>
		</bndbox>
	</object>
</annotation>
