<annotation>
	<folder>大象</folder>
	<filename>007582.jpg</filename>
	<path>D:\下载\大象\007582.jpg</path>
	<source>
		<database>Unknown</database>
	</source>
	<size>
		<width>225</width>
		<height>300</height>
		<depth>3</depth>
	</size>
	<segmented>0</segmented>
	<object>
		<name>elephant</name>
		<pose>Unspecified</pose>
		<truncated>1</truncated>
		<difficult>0</difficult>
		<bndbox>
			<xmin>53</xmin>
			<ymin>53</ymin>
			<xmax>225</xmax>
			<ymax>300</ymax>
		</bndbox>
	</object>
</annotation>
