<annotation>
	<folder>大象</folder>
	<filename>007881.jpg</filename>
	<path>D:\下载\大象\007881.jpg</path>
	<source>
		<database>Unknown</database>
	</source>
	<size>
		<width>300</width>
		<height>205</height>
		<depth>3</depth>
	</size>
	<segmented>0</segmented>
	<object>
		<name>elephant</name>
		<pose>Unspecified</pose>
		<truncated>0</truncated>
		<difficult>0</difficult>
		<bndbox>
			<xmin>70</xmin>
			<ymin>83</ymin>
			<xmax>123</xmax>
			<ymax>128</ymax>
		</bndbox>
	</object>
	<object>
		<name>elephant</name>
		<pose>Unspecified</pose>
		<truncated>0</truncated>
		<difficult>0</difficult>
		<bndbox>
			<xmin>107</xmin>
			<ymin>44</ymin>
			<xmax>203</xmax>
			<ymax>192</ymax>
		</bndbox>
	</object>
	<object>
		<name>elephant</name>
		<pose>Unspecified</pose>
		<truncated>0</truncated>
		<difficult>0</difficult>
		<bndbox>
			<xmin>188</xmin>
			<ymin>18</ymin>
			<xmax>243</xmax>
			<ymax>63</ymax>
		</bndbox>
	</object>
</annotation>
